{
  "frame323": {
    "detector_version": null,
    "image_size": [
      1536,
      1536
    ],
    "data": {
      "nid": {
        "unconfirmed_tracks": {}
      },
      "eau": {
        "0": {
          "bbox": "[529, 11, 633, 155]",
          "conf": 0.8693413,
          "keypoints": [],
          "keypoints conf": [],
          "raw_track_id": 8,
          "source": "AI",
          "state": "alive"
        },
        "1": {
          "bbox": "[1008, 1395, 1130, 1530]",
          "conf": 0.8809507,
          "keypoints": [],
          "keypoints conf": [],
          "raw_track_id": 10,
          "source": "AI",
          "state": "alive"
        },
        "2": {
          "bbox": "[905, 1394, 998, 1533]",
          "conf": 0.8811513,
          "keypoints": [],
          "keypoints conf": [],
          "raw_track_id": 15,
          "source": "AI",
          "state": "alive"
        },
        "3": {
          "bbox": "[390, 8, 492, 156]",
          "conf": 0.84808725,
          "keypoints": [],
          "keypoints conf": [],
          "raw_track_id": 19,
          "source": "AI",
          "state": "alive"
        },
        "unconfirmed_tracks": {}
      },
      "roulette": {
        "0": {
          "bbox": "[925, 432, 1132, 623]",
          "conf": 0.89045,
          "keypoints": [],
          "keypoints conf": [],
          "raw_track_id": 1,
          "source": "AI",
          "state": "alive"
        },
        "1": {
          "bbox": "[395, 919, 598, 1122]",
          "conf": 0.92059267,
          "keypoints": [],
          "keypoints conf": [],
          "raw_track_id": 2,
          "source": "AI",
          "state": "alive"
        },
        "2": {
          "bbox": "[325, 376, 518, 579]",
          "conf": 0.9151293,
          "keypoints": [],
          "keypoints conf": [],
          "raw_track_id": 3,
          "source": "AI",
          "state": "alive"
        },
        "3": {
          "bbox": "[1042, 1010, 1230, 1210]",
          "conf": 0.9158122,
          "keypoints": [],
          "keypoints conf": [],
          "raw_track_id": 7,
          "source": "AI",
          "state": "alive"
        },
        "unconfirmed_tracks": {}
      },
      "mouse": {
        "0": {
          "bbox": "[1350, 585, 1434, 677]",
          "conf": 0.8799615,
          "keypoints": [],
          "keypoints conf": [],
          "raw_track_id": 4,
          "source": "AI",
          "state": "alive"
        },
        "1": {
          "bbox": "[1285, 234, 1360, 330]",
          "conf": 0.87380415,
          "keypoints": [],
          "keypoints conf": [],
          "raw_track_id": 5,
          "source": "AI",
          "state": "alive"
        },
        "2": {
          "bbox": "[141, 1370, 256, 1433]",
          "conf": 0.8751757,
          "keypoints": [],
          "keypoints conf": [],
          "raw_track_id": 9,
          "source": "AI",
          "state": "alive"
        },
        "3": {
          "bbox": "[1074, 192, 1182, 245]",
          "conf": 0.8591486,
          "keypoints": [],
          "keypoints conf": [],
          "raw_track_id": 12,
          "source": "AI",
          "state": "alive"
        },
        "4": {
          "bbox": "[776, 1016, 886, 1071]",
          "conf": 0.8814415,
          "keypoints": [],
          "keypoints conf": [],
          "raw_track_id": 13,
          "source": "AI",
          "state": "alive"
        },
        "5": {
          "bbox": "[1080, 265, 1146, 377]",
          "conf": 0.8854225,
          "keypoints": [],
          "keypoints conf": [],
          "raw_track_id": 29,
          "source": "AI",
          "state": "alive"
        },
        "6": {
          "bbox": "[1300, 362, 1407, 428]",
          "conf": 0.88867736,
          "keypoints": [],
          "keypoints conf": [],
          "raw_track_id": 36,
          "source": "AI",
          "state": "alive"
        },
        "7": {
          "bbox": "[113, 280, 215, 355]",
          "conf": 0.8732381,
          "keypoints": [],
          "keypoints conf": [],
          "raw_track_id": 34,
          "source": "AI",
          "state": "alive"
        },
        "8": {
          "bbox": "[828, 140, 904, 218]",
          "conf": 0.81450665,
          "keypoints": [],
          "keypoints conf": [],
          "raw_track_id": 18,
          "source": "AI",
          "state": "alive"
        },
        "9": {
          "bbox": "[1040, 465, 1093, 580]",
          "conf": 0.82839227,
          "keypoints": [],
          "keypoints conf": [],
          "raw_track_id": 23,
          "source": "AI",
          "state": "alive"
        },
        "unconfirmed_tracks": {}
      },
      "lit": {
        "4": {
          "bbox": "[137, 1191, 253, 1276]",
          "conf": 0.7553708,
          "keypoints": [],
          "keypoints conf": [],
          "raw_track_id": 26,
          "source": "AI",
          "state": "alive"
        },
        "10": {
          "bbox": "[1261, 117, 1383, 200]",
          "conf": 0.77134126,
          "keypoints": [],
          "keypoints conf": [],
          "raw_track_id": 33,
          "source": "AI",
          "state": "alive"
        },
        "13": {
          "bbox": "[1261, 239, 1378, 326]",
          "conf": 0.58717835,
          "keypoints": [],
          "keypoints conf": [],
          "raw_track_id": 20,
          "source": "AI",
          "state": "alive"
        },
        "unconfirmed_tracks": {}
      },
      "mangeoire": {
        "0": {
          "bbox": "[430, 1354, 698, 1528]",
          "conf": 0.8911118,
          "keypoints": [],
          "keypoints conf": [],
          "raw_track_id": 6,
          "source": "AI",
          "state": "alive"
        },
        "1": {
          "bbox": "[839, 5, 1100, 185]",
          "conf": 0.9018708,
          "keypoints": [],
          "keypoints conf": [],
          "raw_track_id": 11,
          "source": "AI",
          "state": "alive"
        },
        "unconfirmed_tracks": {}
      }
    }
  }
}