{
  "frame87": {
    "detector_version": null,
    "image_size": [
      1536,
      1536
    ],
    "data": {
      "nid": {
        "unconfirmed_tracks": {}
      },
      "mouse": {
        "0": {
          "bbox": "[1220, 1331, 1338, 1386]",
          "conf": 0.8532396,
          "keypoints": [],
          "keypoints conf": [],
          "raw_track_id": 4,
          "source": "AI",
          "state": "alive"
        },
        "1": {
          "bbox": "[448, 586, 522, 696]",
          "conf": 0.8971213,
          "keypoints": [],
          "keypoints conf": [],
          "raw_track_id": 5,
          "source": "AI",
          "state": "alive"
        },
        "2": {
          "bbox": "[121, 212, 205, 297]",
          "conf": 0.8840992,
          "keypoints": [],
          "keypoints conf": [],
          "raw_track_id": 9,
          "source": "AI",
          "state": "alive"
        },
        "3": {
          "bbox": "[251, 488, 330, 572]",
          "conf": 0.881321,
          "keypoints": [],
          "keypoints conf": [],
          "raw_track_id": 12,
          "source": "AI",
          "state": "alive"
        },
        "4": {
          "bbox": "[1324, 1338, 1394, 1416]",
          "conf": 0.84380263,
          "keypoints": [],
          "keypoints conf": [],
          "raw_track_id": 13,
          "source": "AI",
          "state": "alive"
        },
        "5": {
          "bbox": "[1375, 137, 1434, 201]",
          "conf": 0.81928617,
          "keypoints": [],
          "keypoints conf": [],
          "raw_track_id": 29,
          "source": "AI",
          "state": "alive"
        },
        "6": {
          "bbox": "[1202, 703, 1265, 809]",
          "conf": 0.8710626,
          "keypoints": [],
          "keypoints conf": [],
          "raw_track_id": 16,
          "source": "AI",
          "state": "alive"
        },
        "7": {
          "bbox": "[1085, 1001, 1198, 1078]",
          "conf": 0.89060724,
          "keypoints": [],
          "keypoints conf": [],
          "raw_track_id": 17,
          "source": "AI",
          "state": "alive"
        },
        "8": {
          "bbox": "[116, 1211, 200, 1306]",
          "conf": 0.8556314,
          "keypoints": [],
          "keypoints conf": [],
          "raw_track_id": 18,
          "source": "AI",
          "state": "alive"
        },
        "9": {
          "bbox": "[471, 1064, 538, 1165]",
          "conf": 0.873928,
          "keypoints": [],
          "keypoints conf": [],
          "raw_track_id": 23,
          "source": "AI",
          "state": "alive"
        },
        "unconfirmed_tracks": {}
      },
      "lit": {
        "0": {
          "bbox": "[1259, 234, 1392, 317]",
          "conf": 0.8082838,
          "keypoints": [],
          "keypoints conf": [],
          "raw_track_id": 20,
          "source": "AI",
          "state": "alive"
        },
        "1": {
          "bbox": "[130, 1335, 241, 1421]",
          "conf": 0.70019436,
          "keypoints": [],
          "keypoints conf": [],
          "raw_track_id": 21,
          "source": "AI",
          "state": "alive"
        },
        "4": {
          "bbox": "[131, 1191, 245, 1289]",
          "conf": 0.6385802,
          "keypoints": [],
          "keypoints conf": [],
          "raw_track_id": 26,
          "source": "AI",
          "state": "alive"
        },
        "5": {
          "bbox": "[1268, 119, 1378, 190]",
          "conf": 0.6550693,
          "keypoints": [],
          "keypoints conf": [],
          "raw_track_id": 27,
          "source": "AI",
          "state": "alive"
        },
        "unconfirmed_tracks": {}
      },
      "roulette": {
        "0": {
          "bbox": "[924, 425, 1131, 627]",
          "conf": 0.9138382,
          "keypoints": [],
          "keypoints conf": [],
          "raw_track_id": 1,
          "source": "AI",
          "state": "alive"
        },
        "1": {
          "bbox": "[398, 921, 597, 1111]",
          "conf": 0.9062078,
          "keypoints": [],
          "keypoints conf": [],
          "raw_track_id": 2,
          "source": "AI",
          "state": "alive"
        },
        "2": {
          "bbox": "[330, 380, 515, 574]",
          "conf": 0.9091889,
          "keypoints": [],
          "keypoints conf": [],
          "raw_track_id": 3,
          "source": "AI",
          "state": "alive"
        },
        "3": {
          "bbox": "[1044, 1021, 1227, 1208]",
          "conf": 0.8995101,
          "keypoints": [],
          "keypoints conf": [],
          "raw_track_id": 7,
          "source": "AI",
          "state": "alive"
        },
        "unconfirmed_tracks": {}
      },
      "eau": {
        "0": {
          "bbox": "[529, 11, 633, 155]",
          "conf": 0.8596455,
          "keypoints": [],
          "keypoints conf": [],
          "raw_track_id": 8,
          "source": "AI",
          "state": "alive"
        },
        "1": {
          "bbox": "[1010, 1397, 1128, 1529]",
          "conf": 0.8826129,
          "keypoints": [],
          "keypoints conf": [],
          "raw_track_id": 10,
          "source": "AI",
          "state": "alive"
        },
        "2": {
          "bbox": "[906, 1394, 997, 1532]",
          "conf": 0.8702522,
          "keypoints": [],
          "keypoints conf": [],
          "raw_track_id": 15,
          "source": "AI",
          "state": "alive"
        },
        "3": {
          "bbox": "[389, 8, 493, 158]",
          "conf": 0.8451629,
          "keypoints": [],
          "keypoints conf": [],
          "raw_track_id": 19,
          "source": "AI",
          "state": "alive"
        },
        "unconfirmed_tracks": {}
      },
      "mangeoire": {
        "0": {
          "bbox": "[431, 1354, 698, 1531]",
          "conf": 0.8841698,
          "keypoints": [],
          "keypoints conf": [],
          "raw_track_id": 6,
          "source": "AI",
          "state": "alive"
        },
        "1": {
          "bbox": "[840, 2, 1102, 188]",
          "conf": 0.8780529,
          "keypoints": [],
          "keypoints conf": [],
          "raw_track_id": 11,
          "source": "AI",
          "state": "alive"
        },
        "unconfirmed_tracks": {}
      }
    }
  }
}