{
  "frame951": {
    "detector_version": null,
    "image_size": [
      1536,
      1536
    ],
    "data": {
      "lit": {
        "1": {
          "bbox": "[175, 1181, 314, 1278]",
          "conf": 0.8656422,
          "keypoints": [],
          "keypoints conf": [],
          "raw_track_id": 29,
          "source": "AI",
          "state": "alive"
        },
        "15": {
          "bbox": "[1224, 257, 1362, 356]",
          "conf": 0.8307058,
          "keypoints": [],
          "keypoints conf": [],
          "raw_track_id": 34,
          "source": "AI",
          "state": "alive"
        },
        "21": {
          "bbox": "[1276, 132, 1398, 227]",
          "conf": 0.7059731,
          "keypoints": [],
          "keypoints conf": [],
          "raw_track_id": 74,
          "source": "AI",
          "state": "alive"
        },
        "unconfirmed_tracks": {}
      },
      "eau": {
        "0": {
          "bbox": "[1011, 1399, 1130, 1532]",
          "conf": 0.8666722,
          "keypoints": [],
          "keypoints conf": [],
          "raw_track_id": 13,
          "source": "AI",
          "state": "alive"
        },
        "1": {
          "bbox": "[530, 11, 632, 157]",
          "conf": 0.8563681,
          "keypoints": [],
          "keypoints conf": [],
          "raw_track_id": 21,
          "source": "AI",
          "state": "alive"
        },
        "2": {
          "bbox": "[907, 1395, 997, 1533]",
          "conf": 0.86321646,
          "keypoints": [],
          "keypoints conf": [],
          "raw_track_id": 22,
          "source": "AI",
          "state": "alive"
        },
        "3": {
          "bbox": "[391, 8, 493, 157]",
          "conf": 0.8471827,
          "keypoints": [],
          "keypoints conf": [],
          "raw_track_id": 26,
          "source": "AI",
          "state": "alive"
        },
        "unconfirmed_tracks": {}
      },
      "nid": {
        "unconfirmed_tracks": {}
      },
      "mouse": {
        "0": {
          "bbox": "[950, 987, 1030, 1079]",
          "conf": 0.8838623,
          "keypoints": [],
          "keypoints conf": [],
          "raw_track_id": 55,
          "source": "AI",
          "state": "alive"
        },
        "1": {
          "bbox": "[400, 924, 489, 1004]",
          "conf": 0.8677407,
          "keypoints": [],
          "keypoints conf": [],
          "raw_track_id": 60,
          "source": "AI",
          "state": "alive"
        },
        "2": {
          "bbox": "[867, 96, 970, 176]",
          "conf": 0.8218814,
          "keypoints": [],
          "keypoints conf": [],
          "raw_track_id": 47,
          "source": "AI",
          "state": "alive"
        },
        "3": {
          "bbox": "[792, 752, 905, 808]",
          "conf": 0.87660587,
          "keypoints": [],
          "keypoints conf": [],
          "raw_track_id": 10,
          "source": "AI",
          "state": "alive"
        },
        "4": {
          "bbox": "[1127, 133, 1242, 185]",
          "conf": 0.8598404,
          "keypoints": [],
          "keypoints conf": [],
          "raw_track_id": 63,
          "source": "AI",
          "state": "alive"
        },
        "5": {
          "bbox": "[504, 724, 617, 791]",
          "conf": 0.8846491,
          "keypoints": [],
          "keypoints conf": [],
          "raw_track_id": 59,
          "source": "AI",
          "state": "alive"
        },
        "6": {
          "bbox": "[617, 1428, 713, 1487]",
          "conf": 0.83707994,
          "keypoints": [],
          "keypoints conf": [],
          "raw_track_id": 48,
          "source": "AI",
          "state": "alive"
        },
        "7": {
          "bbox": "[355, 864, 451, 916]",
          "conf": 0.87724906,
          "keypoints": [],
          "keypoints conf": [],
          "raw_track_id": 16,
          "source": "AI",
          "state": "alive"
        },
        "8": {
          "bbox": "[150, 1361, 276, 1419]",
          "conf": 0.77270377,
          "keypoints": [],
          "keypoints conf": [],
          "raw_track_id": 72,
          "source": "AI",
          "state": "alive"
        },
        "9": {
          "bbox": "[290, 345, 373, 422]",
          "conf": 0.8603535,
          "keypoints": [],
          "keypoints conf": [],
          "raw_track_id": 18,
          "source": "AI",
          "state": "alive"
        },
        "10": {
          "bbox": "[962, 560, 1100, 612]",
          "conf": 0.8353941,
          "keypoints": [],
          "keypoints conf": [],
          "raw_track_id": 19,
          "source": "AI",
          "state": "alive"
        },
        "11": {
          "bbox": "[1297, 147, 1405, 203]",
          "conf": 0.83673555,
          "keypoints": [],
          "keypoints conf": [],
          "raw_track_id": 23,
          "source": "AI",
          "state": "alive"
        },
        "12": {
          "bbox": "[126, 1365, 195, 1449]",
          "conf": 0.8295522,
          "keypoints": [],
          "keypoints conf": [],
          "raw_track_id": 56,
          "source": "AI",
          "state": "alive"
        },
        "13": {
          "bbox": "[960, 204, 1063, 269]",
          "conf": 0.8786629,
          "keypoints": [],
          "keypoints conf": [],
          "raw_track_id": 41,
          "source": "AI",
          "state": "alive"
        },
        "14": {
          "bbox": "[762, 1376, 888, 1439]",
          "conf": 0.8848469,
          "keypoints": [],
          "keypoints conf": [],
          "raw_track_id": 53,
          "source": "AI",
          "state": "alive"
        },
        "15": {
          "bbox": "[640, 992, 735, 1094]",
          "conf": 0.9029169,
          "keypoints": [],
          "keypoints conf": [],
          "raw_track_id": 62,
          "source": "AI",
          "state": "alive"
        },
        "16": {
          "bbox": "[345, 395, 432, 502]",
          "conf": 0.9011239,
          "keypoints": [],
          "keypoints conf": [],
          "raw_track_id": 17,
          "source": "AI",
          "state": "alive"
        },
        "17": {
          "bbox": "[718, 558, 836, 618]",
          "conf": 0.877503,
          "keypoints": [],
          "keypoints conf": [],
          "raw_track_id": 46,
          "source": "AI",
          "state": "alive"
        },
        "18": {
          "bbox": "[127, 391, 208, 476]",
          "conf": 0.8613872,
          "keypoints": [],
          "keypoints conf": [],
          "raw_track_id": 20,
          "source": "AI",
          "state": "alive"
        },
        "19": {
          "bbox": "[624, 681, 701, 781]",
          "conf": 0.87749183,
          "keypoints": [],
          "keypoints conf": [],
          "raw_track_id": 57,
          "source": "AI",
          "state": "alive"
        },
        "unconfirmed_tracks": {}
      },
      "roulette": {
        "0": {
          "bbox": "[1043, 1012, 1231, 1212]",
          "conf": 0.91130656,
          "keypoints": [],
          "keypoints conf": [],
          "raw_track_id": 1,
          "source": "AI",
          "state": "alive"
        },
        "1": {
          "bbox": "[398, 916, 600, 1115]",
          "conf": 0.91073656,
          "keypoints": [],
          "keypoints conf": [],
          "raw_track_id": 2,
          "source": "AI",
          "state": "alive"
        },
        "2": {
          "bbox": "[922, 432, 1133, 621]",
          "conf": 0.9042907,
          "keypoints": [],
          "keypoints conf": [],
          "raw_track_id": 3,
          "source": "AI",
          "state": "alive"
        },
        "3": {
          "bbox": "[332, 379, 516, 575]",
          "conf": 0.9054002,
          "keypoints": [],
          "keypoints conf": [],
          "raw_track_id": 8,
          "source": "AI",
          "state": "alive"
        },
        "unconfirmed_tracks": {}
      },
      "mangeoire": {
        "0": {
          "bbox": "[428, 1359, 698, 1529]",
          "conf": 0.88136053,
          "keypoints": [],
          "keypoints conf": [],
          "raw_track_id": 6,
          "source": "AI",
          "state": "alive"
        },
        "1": {
          "bbox": "[843, 2, 1109, 186]",
          "conf": 0.8995724,
          "keypoints": [],
          "keypoints conf": [],
          "raw_track_id": 14,
          "source": "AI",
          "state": "alive"
        },
        "unconfirmed_tracks": {}
      }
    }
  }
}