{
  "frame1184": {
    "detector_version": null,
    "image_size": [
      1536,
      1536
    ],
    "data": {
      "lit": {
        "1": {
          "bbox": "[173, 1185, 312, 1280]",
          "conf": 0.6900353,
          "keypoints": [],
          "keypoints conf": [],
          "raw_track_id": 29,
          "source": "AI",
          "state": "alive"
        },
        "15": {
          "bbox": "[1224, 258, 1358, 354]",
          "conf": 0.81815475,
          "keypoints": [],
          "keypoints conf": [],
          "raw_track_id": 34,
          "source": "AI",
          "state": "alive"
        },
        "21": {
          "bbox": "[1264, 136, 1390, 231]",
          "conf": 0.62411547,
          "keypoints": [],
          "keypoints conf": [],
          "raw_track_id": 74,
          "source": "AI",
          "state": "alive"
        },
        "22": {
          "bbox": "[120, 1312, 259, 1429]",
          "conf": 0.86755574,
          "keypoints": [],
          "keypoints conf": [],
          "raw_track_id": 75,
          "source": "AI",
          "state": "alive"
        },
        "unconfirmed_tracks": {}
      },
      "eau": {
        "0": {
          "bbox": "[1012, 1397, 1129, 1530]",
          "conf": 0.87215453,
          "keypoints": [],
          "keypoints conf": [],
          "raw_track_id": 13,
          "source": "AI",
          "state": "alive"
        },
        "1": {
          "bbox": "[530, 9, 635, 158]",
          "conf": 0.8565793,
          "keypoints": [],
          "keypoints conf": [],
          "raw_track_id": 21,
          "source": "AI",
          "state": "alive"
        },
        "2": {
          "bbox": "[907, 1396, 996, 1532]",
          "conf": 0.8618478,
          "keypoints": [],
          "keypoints conf": [],
          "raw_track_id": 22,
          "source": "AI",
          "state": "alive"
        },
        "3": {
          "bbox": "[396, 10, 492, 157]",
          "conf": 0.8207776,
          "keypoints": [],
          "keypoints conf": [],
          "raw_track_id": 26,
          "source": "AI",
          "state": "alive"
        },
        "unconfirmed_tracks": {}
      },
      "nid": {
        "unconfirmed_tracks": {}
      },
      "mouse": {
        "0": {
          "bbox": "[288, 1245, 414, 1315]",
          "conf": 0.8717472,
          "keypoints": [],
          "keypoints conf": [],
          "raw_track_id": 81,
          "source": "AI",
          "state": "alive"
        },
        "1": {
          "bbox": "[354, 809, 465, 861]",
          "conf": 0.8663693,
          "keypoints": [],
          "keypoints conf": [],
          "raw_track_id": 60,
          "source": "AI",
          "state": "alive"
        },
        "2": {
          "bbox": "[997, 78, 1112, 137]",
          "conf": 0.8143002,
          "keypoints": [],
          "keypoints conf": [],
          "raw_track_id": 47,
          "source": "AI",
          "state": "alive"
        },
        "3": {
          "bbox": "[738, 732, 853, 789]",
          "conf": 0.87139684,
          "keypoints": [],
          "keypoints conf": [],
          "raw_track_id": 10,
          "source": "AI",
          "state": "alive"
        },
        "4": {
          "bbox": "[1289, 131, 1369, 196]",
          "conf": 0.8316034,
          "keypoints": [],
          "keypoints conf": [],
          "raw_track_id": 79,
          "source": "AI",
          "state": "alive"
        },
        "5": {
          "bbox": "[230, 1062, 322, 1150]",
          "conf": 0.8600965,
          "keypoints": [],
          "keypoints conf": [],
          "raw_track_id": 59,
          "source": "AI",
          "state": "alive"
        },
        "6": {
          "bbox": "[563, 1034, 654, 1120]",
          "conf": 0.85718036,
          "keypoints": [],
          "keypoints conf": [],
          "raw_track_id": 77,
          "source": "AI",
          "state": "alive"
        },
        "7": {
          "bbox": "[955, 224, 1019, 336]",
          "conf": 0.8955277,
          "keypoints": [],
          "keypoints conf": [],
          "raw_track_id": 16,
          "source": "AI",
          "state": "alive"
        },
        "8": {
          "bbox": "[913, 343, 1034, 408]",
          "conf": 0.8964799,
          "keypoints": [],
          "keypoints conf": [],
          "raw_track_id": 72,
          "source": "AI",
          "state": "alive"
        },
        "9": {
          "bbox": "[1121, 474, 1179, 567]",
          "conf": 0.85999,
          "keypoints": [],
          "keypoints conf": [],
          "raw_track_id": 18,
          "source": "AI",
          "state": "alive"
        },
        "10": {
          "bbox": "[977, 566, 1112, 629]",
          "conf": 0.89953005,
          "keypoints": [],
          "keypoints conf": [],
          "raw_track_id": 19,
          "source": "AI",
          "state": "alive"
        },
        "11": {
          "bbox": "[268, 149, 397, 202]",
          "conf": 0.8420915,
          "keypoints": [],
          "keypoints conf": [],
          "raw_track_id": 80,
          "source": "AI",
          "state": "alive"
        },
        "12": {
          "bbox": "[113, 863, 173, 983]",
          "conf": 0.8960368,
          "keypoints": [],
          "keypoints conf": [],
          "raw_track_id": 56,
          "source": "AI",
          "state": "alive"
        },
        "13": {
          "bbox": "[174, 983, 301, 1032]",
          "conf": 0.83877045,
          "keypoints": [],
          "keypoints conf": [],
          "raw_track_id": 41,
          "source": "AI",
          "state": "alive"
        },
        "14": {
          "bbox": "[1353, 1318, 1430, 1388]",
          "conf": 0.85294104,
          "keypoints": [],
          "keypoints conf": [],
          "raw_track_id": 53,
          "source": "AI",
          "state": "alive"
        },
        "15": {
          "bbox": "[155, 1189, 247, 1285]",
          "conf": 0.8792586,
          "keypoints": [],
          "keypoints conf": [],
          "raw_track_id": 62,
          "source": "AI",
          "state": "alive"
        },
        "16": {
          "bbox": "[161, 488, 226, 604]",
          "conf": 0.8578194,
          "keypoints": [],
          "keypoints conf": [],
          "raw_track_id": 17,
          "source": "AI",
          "state": "alive"
        },
        "17": {
          "bbox": "[912, 718, 1021, 800]",
          "conf": 0.88012004,
          "keypoints": [],
          "keypoints conf": [],
          "raw_track_id": 46,
          "source": "AI",
          "state": "alive"
        },
        "18": {
          "bbox": "[396, 371, 491, 430]",
          "conf": 0.8590949,
          "keypoints": [],
          "keypoints conf": [],
          "raw_track_id": 20,
          "source": "AI",
          "state": "alive"
        },
        "19": {
          "bbox": "[180, 156, 274, 233]",
          "conf": 0.86580634,
          "keypoints": [],
          "keypoints conf": [],
          "raw_track_id": 57,
          "source": "AI",
          "state": "alive"
        },
        "unconfirmed_tracks": {}
      },
      "roulette": {
        "0": {
          "bbox": "[1044, 1013, 1231, 1211]",
          "conf": 0.9093316,
          "keypoints": [],
          "keypoints conf": [],
          "raw_track_id": 1,
          "source": "AI",
          "state": "alive"
        },
        "1": {
          "bbox": "[399, 918, 599, 1112]",
          "conf": 0.91364443,
          "keypoints": [],
          "keypoints conf": [],
          "raw_track_id": 2,
          "source": "AI",
          "state": "alive"
        },
        "2": {
          "bbox": "[926, 435, 1127, 622]",
          "conf": 0.88671315,
          "keypoints": [],
          "keypoints conf": [],
          "raw_track_id": 3,
          "source": "AI",
          "state": "alive"
        },
        "3": {
          "bbox": "[329, 400, 509, 572]",
          "conf": 0.9018542,
          "keypoints": [],
          "keypoints conf": [],
          "raw_track_id": 8,
          "source": "AI",
          "state": "alive"
        },
        "unconfirmed_tracks": {}
      },
      "mangeoire": {
        "0": {
          "bbox": "[421, 1357, 695, 1531]",
          "conf": 0.9060084,
          "keypoints": [],
          "keypoints conf": [],
          "raw_track_id": 6,
          "source": "AI",
          "state": "alive"
        },
        "1": {
          "bbox": "[842, 2, 1112, 183]",
          "conf": 0.88684535,
          "keypoints": [],
          "keypoints conf": [],
          "raw_track_id": 14,
          "source": "AI",
          "state": "alive"
        },
        "unconfirmed_tracks": {}
      }
    }
  }
}